antidote/__init__.py
antidote/py.typed
antidote/_internal/API.py
antidote/_internal/__init__.py
antidote/_internal/config.py
antidote/_internal/localns.py
antidote/_internal/scm_version.py
antidote/_internal/typing.py
antidote/_internal/utils.py
antidote/core/__init__.py
antidote/core/_catalog.py
antidote/core/_debug.py
antidote/core/_inject.py
antidote/core/_injection.py
antidote/core/_objects.py
antidote/core/_scope.py
antidote/core/_test.py
antidote/core/_wiring.py
antidote/core/annotation.py
antidote/core/data.py
antidote/core/exceptions.py
antidote/core/provider.py
antidote/core/scope.py
antidote/core/utils.py
antidote/core/wiring.py
antidote/core/_raw/__init__.py
antidote/core/_raw/onion.py
antidote/core/_raw/wrapper.py
antidote/lib/__init__.py
antidote/lib/injectable_ext/__init__.py
antidote/lib/injectable_ext/_internal.py
antidote/lib/injectable_ext/_provider.py
antidote/lib/interface_ext/__init__.py
antidote/lib/interface_ext/_function.py
antidote/lib/interface_ext/_interface.py
antidote/lib/interface_ext/_internal.py
antidote/lib/interface_ext/_provider.py
antidote/lib/interface_ext/predicate.py
antidote/lib/interface_ext/qualifier.py
antidote/lib/lazy_ext/__init__.py
antidote/lib/lazy_ext/_const.py
antidote/lib/lazy_ext/_lazy.py
antidote/lib/lazy_ext/_provider.py
antidote-2.0.0.dist-info/LICENSE
antidote-2.0.0.dist-info/METADATA
antidote-2.0.0.dist-info/WHEEL
antidote-2.0.0.dist-info/top_level.txt
antidote-2.0.0.dist-info/RECORD
