Metadata-Version: 2.1
Name: antidote
Version: 2.0.0
Summary: Dependency injection.
Home-page: https://github.com/Finistere/antidote
Author: Benjamin Rabier
License: MIT
Keywords: dependency injection
Classifier: Development Status :: 5 - Production/Stable 
Classifier: Intended Audience :: Developers
Classifier: Natural Language :: English
Classifier: License :: OSI Approved :: MIT License
Classifier: Programming Language :: Python
Classifier: Programming Language :: Python :: 3
Classifier: Programming Language :: Python :: 3.7
Classifier: Programming Language :: Python :: 3.8
Classifier: Programming Language :: Python :: 3.9
Classifier: Programming Language :: Python :: 3.10
Classifier: Programming Language :: Python :: Implementation :: CPython
Classifier: Programming Language :: Python :: Implementation :: PyPy
Requires-Python: >=3.7,<4
License-File: LICENSE
Requires-Dist: typing-extensions
